LICENSE.txt
MANIFEST.in
README.md
setup.cfg
setup.py
kntgen/__init__.py
kntgen/__main__.py
kntgen/bash_helpers.py
kntgen/cmd.py
kntgen/collection_helpers.py
kntgen/constants.py
kntgen/encoder.py
kntgen/file_helpers.py
kntgen/parallel_helpers.py
kntgen/parser_helpers.py
kntgen/pasteboard.py
kntgen/printer.py
kntgen/str_helpers.py
kntgen/template.py
kntgen.egg-info/PKG-INFO
kntgen.egg-info/SOURCES.txt
kntgen.egg-info/dependency_links.txt
kntgen.egg-info/entry_points.txt
kntgen.egg-info/requires.txt
kntgen.egg-info/top_level.txt
kntgen/bloc/__init__.py
kntgen/bloc/bloc_cmd.py
kntgen/bloc/bloc_template.py
kntgen/json_to_dart/__init__.py
kntgen/json_to_dart/json_cmd.py
kntgen/model/__init__.py
kntgen/model/bloc.py
kntgen/model/exception.py
kntgen/model/figma_models.py
kntgen/model/json.py
kntgen/model/network.py
kntgen/model/postman.py
kntgen/model/project_info.py
kntgen/model/ui_config.py
kntgen/model/flutter/__init__.py
kntgen/model/flutter/flutter_base_widgets.py
kntgen/model/flutter/flutter_raw_widget.py
kntgen/model/flutter/flutter_specific_widgets.py
kntgen/network/__init__.py
kntgen/network/network_cmd.py
kntgen/network/network_template.py
kntgen/ui/__init__.py
kntgen/ui/cheat_sheet.py
kntgen/ui/figma.py
kntgen/ui/figma_ui_generator.py
kntgen/ui/flutter_generator.py
kntgen/ui/flutter_parser.py
kntgen/ui/ui_external_source.py
kntgen_templates/__init__.py
kntgen_templates/bloc/__init__.py
kntgen_templates/bloc/bloc.dart
kntgen_templates/bloc/bloc_test.dart
kntgen_templates/bloc/sample_input/__init__.py
kntgen_templates/bloc/sample_input/sample_bloc.json
kntgen_templates/bloc/sample_input/sample_bloc.yaml
kntgen_templates/json_to_dart/__init__.py
kntgen_templates/json_to_dart/json.dart
kntgen_templates/json_to_dart/sample_input/__init__.py
kntgen_templates/json_to_dart/sample_input/sample.json
kntgen_templates/network/__init__.py
kntgen_templates/network/model/network_models.dart
kntgen_templates/network/model/request_model.dart
kntgen_templates/network/model/response_model.dart
kntgen_templates/network/other/fixture_reader.dart
kntgen_templates/network/repo/cloud_repo.dart
kntgen_templates/network/repo/data_cloud_repo.dart
