Metadata-Version: 2.1
Name: kntgen
Version: 1.0.14
Summary: A generator for Dart code using by Appixi's projects
Home-page: https://github.com/appixi/knt_dart_generator
Author: kiendtvt1411
Author-email: dtvtdevelopersk58@gmail.com
License: MIT
Platform: UNKNOWN
Classifier: Programming Language :: Python :: 3
Classifier: License :: OSI Approved :: MIT License
Classifier: Operating System :: OS Independent
Requires-Python: >=3.7
License-File: LICENSE.txt
